pyapic/APIConnect.py
pyapic/__init__.py
pyapic-0.0.3.dist-info/LICENSE
pyapic-0.0.3.dist-info/METADATA
pyapic-0.0.3.dist-info/WHEEL
pyapic-0.0.3.dist-info/top_level.txt
pyapic-0.0.3.dist-info/RECORD
