Metadata-Version: 2.1
Name: pyapic
Version: 0.0.3
Summary: API Connect 2018 Management API
Home-page: https://github.com/jmorenoamor/pyapic
Author: Jesús Moreno Amor
Author-email: jesus@morenoamor.com
License: UNKNOWN
Platform: UNKNOWN
Classifier: Programming Language :: Python :: 3
Classifier: License :: OSI Approved :: MIT License
Classifier: Operating System :: OS Independent
Requires-Python: >=3.6
Requires-Dist: oyaml
Requires-Dist: requests
Requires-Dist: python-dateutil
